[{"delegation":{"circonscription":{"circ_id":"610","circ_name":"قفصة"},"deleg_id":"55","deleg_name":"أم العرائس"},"pcenter_id":"001","pcenter_name":"م إبتدائية 14 جانفي أم العرائس - المحطة"},{"delegation":{"circonscription":{"circ_id":"610","circ_name":"قفصة"},"deleg_id":"55","deleg_name":"أم العرائس"},"pcenter_id":"002","pcenter_name":"م إبتدائية البركة أم العرائس - المحطة"},{"delegation":{"circonscription":{"circ_id":"610","circ_name":"قفصة"},"deleg_id":"55","deleg_name":"أم العرائس"},"pcenter_id":"003","pcenter_name":"م إبتدائية الحي العمالي ام العرائس - المحطة"},{"delegation":{"circonscription":{"circ_id":"610","circ_name":"قفصة"},"deleg_id":"55","deleg_name":"أم العرائس"},"pcenter_id":"004","pcenter_name":"م إبتدائية الدوارة ام العرائس"},{"delegation":{"circonscription":{"circ_id":"610","circ_name":"قفصة"},"deleg_id":"55","deleg_name":"أم العرائس"},"pcenter_id":"005","pcenter_name":"م إبتدائية الشنوفية أم العرائس"},{"delegation":{"circonscription":{"circ_id":"610","circ_name":"قفصة"},"deleg_id":"55","deleg_name":"أم العرائس"},"pcenter_id":"006","pcenter_name":"م إبتدائية العهد الجديد أم العرائس"},{"delegation":{"circonscription":{"circ_id":"610","circ_name":"قفصة"},"deleg_id":"55","deleg_name":"أم العرائس"},"pcenter_id":"007","pcenter_name":"م إبتدائية القطع أم العرائس"},{"delegation":{"circonscription":{"circ_id":"610","circ_name":"قفصة"},"deleg_id":"55","deleg_name":"أم العرائس"},"pcenter_id":"008","pcenter_name":"م إبتدائية الكدية أم العرائس - سيدي بو بكر"},{"delegation":{"circonscription":{"circ_id":"610","circ_name":"قفصة"},"deleg_id":"55","deleg_name":"أم العرائس"},"pcenter_id":"009","pcenter_name":"م إبتدائية الكسيلة ام العرائس"},{"delegation":{"circonscription":{"circ_id":"610","circ_name":"قفصة"},"deleg_id":"55","deleg_name":"أم العرائس"},"pcenter_id":"010","pcenter_name":"م إبتدائية اللوزة أم العرائس - الشنوفية"},{"delegation":{"circonscription":{"circ_id":"610","circ_name":"قفصة"},"deleg_id":"55","deleg_name":"أم العرائس"},"pcenter_id":"011","pcenter_name":"م إبتدائية المحطة ام العرائس"},{"delegation":{"circonscription":{"circ_id":"610","circ_name":"قفصة"},"deleg_id":"55","deleg_name":"أم العرائس"},"pcenter_id":"012","pcenter_name":"م إبتدائية المنجم ام العرائس - المحطة"},{"delegation":{"circonscription":{"circ_id":"610","circ_name":"قفصة"},"deleg_id":"55","deleg_name":"أم العرائس"},"pcenter_id":"013","pcenter_name":"م إبتدائية ام الاقصاب ام العرائس"},{"delegation":{"circonscription":{"circ_id":"610","circ_name":"قفصة"},"deleg_id":"55","deleg_name":"أم العرائس"},"pcenter_id":"014","pcenter_name":"م إبتدائية أولااد السّاعي - سيدي بو بكر"},{"delegation":{"circonscription":{"circ_id":"610","circ_name":"قفصة"},"deleg_id":"55","deleg_name":"أم العرائس"},"pcenter_id":"015","pcenter_name":"م إبتدائية بن عمار أم العرائس - السواطير"},{"delegation":{"circonscription":{"circ_id":"610","circ_name":"قفصة"},"deleg_id":"55","deleg_name":"أم العرائس"},"pcenter_id":"016","pcenter_name":"م إبتدائية حشانة ام العرائس"},{"delegation":{"circonscription":{"circ_id":"610","circ_name":"قفصة"},"deleg_id":"55","deleg_name":"أم العرائس"},"pcenter_id":"017","pcenter_name":"م إبتدائية حي الزهور أم العرائس - المحطة"},{"delegation":{"circonscription":{"circ_id":"610","circ_name":"قفصة"},"deleg_id":"55","deleg_name":"أم العرائس"},"pcenter_id":"018","pcenter_name":"م إبتدائية حي السوالمية أم العرائس - المحطة"},{"delegation":{"circonscription":{"circ_id":"610","circ_name":"قفصة"},"deleg_id":"55","deleg_name":"أم العرائس"},"pcenter_id":"019","pcenter_name":"م إبتدائية خالد ابن الوليد أم العرائس - سيدي بوبكر"},{"delegation":{"circonscription":{"circ_id":"610","circ_name":"قفصة"},"deleg_id":"55","deleg_name":"أم العرائس"},"pcenter_id":"020","pcenter_name":"م إبتدائية سيدي بوبكر ام العرائس"},{"delegation":{"circonscription":{"circ_id":"610","circ_name":"قفصة"},"deleg_id":"55","deleg_name":"أم العرائس"},"pcenter_id":"021","pcenter_name":"م إبتدائية طارق ابن زياد أم العرائس"},{"delegation":{"circonscription":{"circ_id":"610","circ_name":"قفصة"},"deleg_id":"55","deleg_name":"أم العرائس"},"pcenter_id":"022","pcenter_name":"م إبتدائية عقلة احمد ام العرائس - أم الأقصاب"},{"delegation":{"circonscription":{"circ_id":"610","circ_name":"قفصة"},"deleg_id":"55","deleg_name":"أم العرائس"},"pcenter_id":"023","pcenter_name":"م إبتدائية هنشير القلال أم العرائس - الدوارة"},{"delegation":{"circonscription":{"circ_id":"610","circ_name":"قفصة"},"deleg_id":"55","deleg_name":"أم العرائس"},"pcenter_id":"091","pcenter_name":"م إعدادية إبن منظور أم العرائس*"}]