{"circonscription":"320","delegation":"54","pcenter":"","eligible_voters":"1892","voter_turnout":"1540","delivred_ballots":"1910","blank_ballots":"20","unused_ballots":"359","cancelled_ballots":"71","damaged_ballots":"11","correct_ballots":"1449","partyresults":[{"number":"34","name":"قائمة الحزب الليبرالي المغاربي","votes":"3 ","percentage":"0.21 "},{"number":"1","name":"قائمة حزب الأمانة","votes":"5","percentage":"0.35"},{"number":"35","name":"قائمة حزب الكرامة والمساواة","votes":"0 ","percentage":"0 "},{"number":"2","name":"قائمة حركة الوطنيين الديمقراطيين","votes":"17","percentage":"1.17"},{"number":"36","name":"قائمة المستقلون","votes":"3 ","percentage":"0.21 "},{"number":"3","name":"قائمة حزب العدالة والتنمية (تونس لكل التونسيين)","votes":"4","percentage":"0.28"},{"number":"37","name":"قائمة الحزب الشعبي للحرية والتقدّم","votes":"1 ","percentage":"0.07 "},{"number":"4","name":"الشباب المتحضر الطموح","votes":"3","percentage":"0.21"},{"number":"38","name":"قائمة الاتحاد الديمقراطي الوحدوي","votes":"1 ","percentage":"0.07 "},{"number":"5","name":"قائمة حزب الانفتاح والوفاء","votes":"2","percentage":"0.14"},{"number":"39","name":"قائمة حركة الشعب","votes":"2 ","percentage":"0.14 "},{"number":"6","name":"قائمة  الحركة الإصلاحية التونسية","votes":"2","percentage":"0.14"},{"number":"40","name":"قائمة الصدق","votes":"4 ","percentage":"0.28 "},{"number":"7","name":"قائمة حركة الوحدة الشعبية","votes":"6","percentage":"0.41"},{"number":"41","name":"قائمةحزب النضال التقدمي","votes":"2 ","percentage":"0.14 "},{"number":"8","name":"قائمة لنفتح معا باب الأمل","votes":"2","percentage":"0.14"},{"number":"42","name":"قائمة الحق والمسؤولية","votes":"0 ","percentage":"0 "},{"number":"9","name":"قائمة العمل والكفاءة","votes":"2","percentage":"0.14"},{"number":"43","name":"قائمة سيادة الشعب","votes":"7 ","percentage":"0.48 "},{"number":"10","name":"قائمة العدالة والمصالحة","votes":"0","percentage":"0"},{"number":"44","name":"قائمة حزب المؤتمر من أجل الجمهورية","votes":"36 ","percentage":"2.48 "},{"number":"11","name":"قائمة الاتحاد الوطني الحر","votes":"29","percentage":"2"},{"number":"45","name":"قائمة رسالة تونس إلى العالم","votes":"0 ","percentage":"0 "},{"number":"12","name":" قائمة الحزب الإصلاحي الدستوري","votes":"54","percentage":"3.73"},{"number":"46","name":"قائمة القطب الديمقراطي الحداثي","votes":"13 ","percentage":"0.9 "},{"number":"13","name":"قائمة الحزب الدستوري الجديد","votes":"6","percentage":"0.41"},{"number":"47","name":"قائمة حزب الخضر للتقدّم (الخضر)","votes":"29 ","percentage":"2 "},{"number":"14","name":"قائمة حزب العمال الشيوعي التونسي (البديل الثوري) ","votes":"2","percentage":"0.14"},{"number":"48","name":"قائمة التكتل الديمقراطي من أجل العمل والحريات","votes":"170 ","percentage":"11.73 "},{"number":"15","name":"قائمة إرادة الشعب","votes":"6","percentage":"0.41"},{"number":"49","name":"قائمة الاتحاد الشعبي الجمهوري","votes":"1 ","percentage":"0.07 "},{"number":"16","name":"قائمة التآلف الجمهوري","votes":"2","percentage":"0.14"},{"number":"50","name":"قائمة حركة النهضة","votes":"474 ","percentage":"32.71 "},{"number":"17","name":"قائمة حزب العدالة والمساواة","votes":"12","percentage":"0.83"},{"number":"51","name":"قائمة الأمــــة","votes":"2 ","percentage":"0.14 "},{"number":"18","name":"قائمة النضال الاجتماعي","votes":"2","percentage":"0.14"},{"number":"52","name":"قائمة حركة الشعب الوحدوية التقدمية","votes":"4 ","percentage":"0.28 "},{"number":"19","name":"قائمة الوحدة الوطنية","votes":"95","percentage":"6.56"},{"number":"53","name":"قائمة الوحدة هدفنا","votes":"3 ","percentage":"0.21 "},{"number":"20","name":"قائمة حزب التحالف الوطني للسلم والنماء","votes":"2","percentage":"0.14"},{"number":"54","name":" قائمة حركة الكرامة والتنمية","votes":"3 ","percentage":"0.21 "},{"number":"21","name":"قائمة الحزب الديمقراطي التقدمي","votes":"22","percentage":"1.52"},{"number":"55","name":"قائمة تونس الجديدة  ","votes":"0 ","percentage":"0 "},{"number":"22","name":"قائمة حزب الوحدة الشعبية","votes":"4","percentage":"0.28"},{"number":"56","name":"قائمة الحراك المستقل بالمنستير","votes":"3 ","percentage":"0.21 "},{"number":"23","name":"قائمة التأسيس للمواطنة والعدالة","votes":"0","percentage":"0"},{"number":"57","name":"قائمة حزب المجد","votes":"3 ","percentage":"0.21 "},{"number":"24","name":"قائمة الكرامة والعدالة والسلم الاجتماعية","votes":"9","percentage":"0.62"},{"number":"58","name":"قائمة الخمسة","votes":"15 ","percentage":"1.04 "},{"number":"25","name":"قائمة حزب الإصلاح والتنمية","votes":"0","percentage":"0"},{"number":"59","name":"قائمة الائتلاف التحرري","votes":"1 ","percentage":"0.07 "},{"number":"26","name":"قائمة الائتلاف الديمقراطي المستقل - طريق السلامة -","votes":"1","percentage":"0.07"},{"number":"60","name":"قائمة العريضة الشعبية للحرية والعدالة والتنمية","votes":"16 ","percentage":"1.1 "},{"number":"27","name":"قائمة حزب آفاق تونس","votes":"8","percentage":"0.55"},{"number":"61","name":"قائمة الجرأة والطموح","votes":"10 ","percentage":"0.69 "},{"number":"28","name":"قائمة الرقي لتونس","votes":"2","percentage":"0.14"},{"number":"62","name":"قائمة الرباط","votes":"3 ","percentage":"0.21 "},{"number":"29","name":"قائمة ثورة حتى النصر","votes":"2","percentage":"0.14"},{"number":"63","name":"قائمة حزب العمل التونسي","votes":"22 ","percentage":"1.52 "},{"number":"30","name":"قائمة بلدي الحبيب","votes":"2","percentage":"0.14"},{"number":"64","name":"قائمة الأمـــل","votes":"185 ","percentage":"12.77 "},{"number":"31","name":"قائمة حركة الديمقراطيين الاشتراكيين","votes":"11","percentage":"0.76"},{"number":"65","name":"قائمة الشمـــوخ","votes":"6 ","percentage":"0.41 "},{"number":"32","name":"قائمة الحســــم","votes":"1","percentage":"0.07"},{"number":"66","name":"قائمة حزب المبادرة","votes":"81 ","percentage":"5.59 "},{"number":"33","name":"قائمة حزب الأمة الثقافي الوحدوي","votes":"31","percentage":"2.14"}],"pcenter_id":"014"}