{"circonscription":"630","delegation":"54","pcenter":"","eligible_voters":"2162","voter_turnout":"1988","delivred_ballots":"2322","blank_ballots":"33","unused_ballots":"322","cancelled_ballots":"22","damaged_ballots":"12","correct_ballots":"1933","partyresults":[{"number":"14","name":"قائمة التآلف الجمهوري","votes":"2 ","percentage":"0.1 "},{"number":"1","name":"قائمة الحزب الديمقراطي التقدمي","votes":"34","percentage":"1.76"},{"number":"15","name":"قائمة الوفــاء","votes":"65 ","percentage":"3.36 "},{"number":"2","name":"قائمة حزب العمال الشيوعي التونسي (البديل الثوري) ","votes":"6","percentage":"0.31"},{"number":"16","name":"قائمة الكرامة","votes":"37 ","percentage":"1.91 "},{"number":"3","name":"قائمة تونس لنا ونحن لها","votes":"1","percentage":"0.05"},{"number":"17","name":"قائمة التقدمية المستقلة","votes":"19 ","percentage":"0.98 "},{"number":"4","name":"قائمة حركة الديمقراطيين الاشتراكيين","votes":"6","percentage":"0.31"},{"number":"18","name":"قائمة الفلسفة","votes":"1 ","percentage":"0.05 "},{"number":"5","name":"قائمة حزب التكتل","votes":"5","percentage":"0.26"},{"number":"19","name":"قائمة حزب التحالف الوطني للسلم والنماء","votes":"1 ","percentage":"0.05 "},{"number":"6","name":"قائمة القطب الديمقراطي الحداثي","votes":"7","percentage":"0.36"},{"number":"20","name":"قائمة الوحدة الوطنية","votes":"10 ","percentage":"0.52 "},{"number":"7","name":"قائمة 14جانفي","votes":"2","percentage":"0.1"},{"number":"21","name":"قائمة الكادحة المستقلة","votes":"2 ","percentage":"0.1 "},{"number":"8","name":"قائمة حزب المؤتمر من أجل الجمهورية","votes":"397","percentage":"20.54"},{"number":"22","name":"قائمة العريضة الشعبية للحرية والعدالة والتنمية","votes":"13 ","percentage":"0.67 "},{"number":"9","name":"قائمة الاتحاد الوطني الحر","votes":"3","percentage":"0.16"},{"number":"23","name":"قائمة حركة النهضة","votes":"1279 ","percentage":"66.17 "},{"number":"10","name":"قائمة حركة الشعب الوحدوية التقدمية","votes":"3","percentage":"0.16"},{"number":"24","name":"قائمة إرادة الحياة","votes":"15 ","percentage":"0.78 "},{"number":"11","name":"قائمة حزب الوحدة الشعبية","votes":"13","percentage":"0.67"},{"number":"25","name":"قائمة الاتحاد الديمقراطي الوحدوي","votes":"4 ","percentage":"0.21 "},{"number":"12","name":"قائمة المبادرة الحرّة","votes":"2","percentage":"0.1"},{"number":"26","name":"قائمة الإصلاح والمصالحة ","votes":"5 ","percentage":"0.26 "},{"number":"13","name":" قائمة حزب الخضر للتقدّم (الخضر)","votes":"1","percentage":"0.05"}],"pcenter_id":"006"}