[{"delegation":{"circonscription":{"circ_id":"520","circ_name":"مدنين"},"deleg_id":"53","deleg_name":"بني خداش"},"pcenter_id":"001","pcenter_name":"م إبتدائية 2مارس34بني خداش"},{"delegation":{"circonscription":{"circ_id":"520","circ_name":"مدنين"},"deleg_id":"53","deleg_name":"بني خداش"},"pcenter_id":"002","pcenter_name":"م إبتدائية آبار الخيل - وادي الخيل"},{"delegation":{"circonscription":{"circ_id":"520","circ_name":"مدنين"},"deleg_id":"53","deleg_name":"بني خداش"},"pcenter_id":"003","pcenter_name":"م إبتدائية البحيرة"},{"delegation":{"circonscription":{"circ_id":"520","circ_name":"مدنين"},"deleg_id":"53","deleg_name":"بني خداش"},"pcenter_id":"004","pcenter_name":"م إبتدائية البطومة - البحيرة"},{"delegation":{"circonscription":{"circ_id":"520","circ_name":"مدنين"},"deleg_id":"53","deleg_name":"بني خداش"},"pcenter_id":"005","pcenter_name":"م إبتدائية البقباق - ورجيجن"},{"delegation":{"circonscription":{"circ_id":"520","circ_name":"مدنين"},"deleg_id":"53","deleg_name":"بني خداش"},"pcenter_id":"006","pcenter_name":"م إبتدائية البنية"},{"delegation":{"circonscription":{"circ_id":"520","circ_name":"مدنين"},"deleg_id":"53","deleg_name":"بني خداش"},"pcenter_id":"007","pcenter_name":"م إبتدائية الخير - زمور"},{"delegation":{"circonscription":{"circ_id":"520","circ_name":"مدنين"},"deleg_id":"53","deleg_name":"بني خداش"},"pcenter_id":"008","pcenter_name":"م إبتدائية الدخيلة"},{"delegation":{"circonscription":{"circ_id":"520","circ_name":"مدنين"},"deleg_id":"53","deleg_name":"بني خداش"},"pcenter_id":"009","pcenter_name":"م إبتدائية الشوامخ - الحميمة"},{"delegation":{"circonscription":{"circ_id":"520","circ_name":"مدنين"},"deleg_id":"53","deleg_name":"بني خداش"},"pcenter_id":"010","pcenter_name":"م إبتدائية الفجيج"},{"delegation":{"circonscription":{"circ_id":"520","circ_name":"مدنين"},"deleg_id":"53","deleg_name":"بني خداش"},"pcenter_id":"011","pcenter_name":"م إبتدائية القصبة - بني خداش"},{"delegation":{"circonscription":{"circ_id":"520","circ_name":"مدنين"},"deleg_id":"53","deleg_name":"بني خداش"},"pcenter_id":"012","pcenter_name":"م إبتدائية القصر الجديد"},{"delegation":{"circonscription":{"circ_id":"520","circ_name":"مدنين"},"deleg_id":"53","deleg_name":"بني خداش"},"pcenter_id":"013","pcenter_name":"م إبتدائية القطار - القصر الجديد"},{"delegation":{"circonscription":{"circ_id":"520","circ_name":"مدنين"},"deleg_id":"53","deleg_name":"بني خداش"},"pcenter_id":"014","pcenter_name":"م إبتدائية المظهار - المنزلة"},{"delegation":{"circonscription":{"circ_id":"520","circ_name":"مدنين"},"deleg_id":"53","deleg_name":"بني خداش"},"pcenter_id":"015","pcenter_name":"م إبتدائية حلق الجمل - الحميمة"},{"delegation":{"circonscription":{"circ_id":"520","circ_name":"مدنين"},"deleg_id":"53","deleg_name":"بني خداش"},"pcenter_id":"016","pcenter_name":"م إبتدائية دخيلة سطوط - القصر الجديد"},{"delegation":{"circonscription":{"circ_id":"520","circ_name":"مدنين"},"deleg_id":"53","deleg_name":"بني خداش"},"pcenter_id":"017","pcenter_name":"م إبتدائية دمر - بني خداش"},{"delegation":{"circonscription":{"circ_id":"520","circ_name":"مدنين"},"deleg_id":"53","deleg_name":"بني خداش"},"pcenter_id":"018","pcenter_name":"م إبتدائية زمور"},{"delegation":{"circonscription":{"circ_id":"520","circ_name":"مدنين"},"deleg_id":"53","deleg_name":"بني خداش"},"pcenter_id":"019","pcenter_name":"م إبتدائية سيدي منصور - بني خداش"},{"delegation":{"circonscription":{"circ_id":"520","circ_name":"مدنين"},"deleg_id":"53","deleg_name":"بني خداش"},"pcenter_id":"020","pcenter_name":"م إبتدائية شعبة فاضل - الزغاية"},{"delegation":{"circonscription":{"circ_id":"520","circ_name":"مدنين"},"deleg_id":"53","deleg_name":"بني خداش"},"pcenter_id":"021","pcenter_name":"م إبتدائية عزيزة - البنية"},{"delegation":{"circonscription":{"circ_id":"520","circ_name":"مدنين"},"deleg_id":"53","deleg_name":"بني خداش"},"pcenter_id":"022","pcenter_name":"م إبتدائية قصر الجراء - الزغاية"},{"delegation":{"circonscription":{"circ_id":"520","circ_name":"مدنين"},"deleg_id":"53","deleg_name":"بني خداش"},"pcenter_id":"023","pcenter_name":"م إبتدائية قصر الجوامع - رحالة"},{"delegation":{"circonscription":{"circ_id":"520","circ_name":"مدنين"},"deleg_id":"53","deleg_name":"بني خداش"},"pcenter_id":"024","pcenter_name":"م إبتدائية قصر الحلوف - المنزلة"},{"delegation":{"circonscription":{"circ_id":"520","circ_name":"مدنين"},"deleg_id":"53","deleg_name":"بني خداش"},"pcenter_id":"025","pcenter_name":"م إبتدائية قصر الخراشفة - وادي الخيل"},{"delegation":{"circonscription":{"circ_id":"520","circ_name":"مدنين"},"deleg_id":"53","deleg_name":"بني خداش"},"pcenter_id":"026","pcenter_name":"م إبتدائية قصرالمحاضة - البنية"},{"delegation":{"circonscription":{"circ_id":"520","circ_name":"مدنين"},"deleg_id":"53","deleg_name":"بني خداش"},"pcenter_id":"027","pcenter_name":"م إبتدائية قليب ذياب - الزغاية"},{"delegation":{"circonscription":{"circ_id":"520","circ_name":"مدنين"},"deleg_id":"53","deleg_name":"بني خداش"},"pcenter_id":"028","pcenter_name":"م إبتدائية قمانة - رحالة"},{"delegation":{"circonscription":{"circ_id":"520","circ_name":"مدنين"},"deleg_id":"53","deleg_name":"بني خداش"},"pcenter_id":"029","pcenter_name":"م إبتدائية منزلة مقر - المنزلة"},{"delegation":{"circonscription":{"circ_id":"520","circ_name":"مدنين"},"deleg_id":"53","deleg_name":"بني خداش"},"pcenter_id":"030","pcenter_name":"م إبتدائية هنشير الماجل - القصر الجديد"},{"delegation":{"circonscription":{"circ_id":"520","circ_name":"مدنين"},"deleg_id":"53","deleg_name":"بني خداش"},"pcenter_id":"031","pcenter_name":"م إبتدائية وجه اللغاء - البنية"},{"delegation":{"circonscription":{"circ_id":"520","circ_name":"مدنين"},"deleg_id":"53","deleg_name":"بني خداش"},"pcenter_id":"032","pcenter_name":"م إبتدائية ورجيجن"},{"delegation":{"circonscription":{"circ_id":"520","circ_name":"مدنين"},"deleg_id":"53","deleg_name":"بني خداش"},"pcenter_id":"091","pcenter_name":"م إعدادية الفاضل بن عاشور ببني خـداش*"}]