[{"circonscription":{"circ_id":"120","circ_name":"أريانة"},"deleg_id":"51","deleg_name":"اريانة المدينة"},{"circonscription":{"circ_id":"120","circ_name":"أريانة"},"deleg_id":"52","deleg_name":"سكرة"},{"circonscription":{"circ_id":"120","circ_name":"أريانة"},"deleg_id":"53","deleg_name":"روّاد"},{"circonscription":{"circ_id":"120","circ_name":"أريانة"},"deleg_id":"54","deleg_name":"قلعة الأندلس"},{"circonscription":{"circ_id":"120","circ_name":"أريانة"},"deleg_id":"55","deleg_name":"سيدي ثابت"},{"circonscription":{"circ_id":"120","circ_name":"أريانة"},"deleg_id":"56","deleg_name":"حي التضامن"},{"circonscription":{"circ_id":"120","circ_name":"أريانة"},"deleg_id":"57","deleg_name":"المنيهلة"}]