[{"delegation":{"circonscription":{"circ_id":"240","circ_name":"سليانـــة"},"deleg_id":"56","deleg_name":"بورويس"},"pcenter_id":"001","pcenter_name":"م إبتدائية   14 جانفي بورويس - بورويس المدينة"},{"delegation":{"circonscription":{"circ_id":"240","circ_name":"سليانـــة"},"deleg_id":"56","deleg_name":"بورويس"},"pcenter_id":"002","pcenter_name":"م إبتدائية  2مارس 34 سيدي بورويس - بورويس المدينة"},{"delegation":{"circonscription":{"circ_id":"240","circ_name":"سليانـــة"},"deleg_id":"56","deleg_name":"بورويس"},"pcenter_id":"003","pcenter_name":"م إبتدائية التريشة"},{"delegation":{"circonscription":{"circ_id":"240","circ_name":"سليانـــة"},"deleg_id":"56","deleg_name":"بورويس"},"pcenter_id":"004","pcenter_name":"م إبتدائية الحياة - محطة الكريب"},{"delegation":{"circonscription":{"circ_id":"240","circ_name":"سليانـــة"},"deleg_id":"56","deleg_name":"بورويس"},"pcenter_id":"005","pcenter_name":"م إبتدائية الرويسين الجديدة - عين عاشور"},{"delegation":{"circonscription":{"circ_id":"240","circ_name":"سليانـــة"},"deleg_id":"56","deleg_name":"بورويس"},"pcenter_id":"006","pcenter_name":"م إبتدائية الرويسين القديمة - عين عاشور"},{"delegation":{"circonscription":{"circ_id":"240","circ_name":"سليانـــة"},"deleg_id":"56","deleg_name":"بورويس"},"pcenter_id":"007","pcenter_name":"م إبتدائية العباسي"},{"delegation":{"circonscription":{"circ_id":"240","circ_name":"سليانـــة"},"deleg_id":"56","deleg_name":"بورويس"},"pcenter_id":"008","pcenter_name":"م إبتدائية النشم - بورويس الجنوبية"},{"delegation":{"circonscription":{"circ_id":"240","circ_name":"سليانـــة"},"deleg_id":"56","deleg_name":"بورويس"},"pcenter_id":"009","pcenter_name":"م إبتدائية أولاد يوسف - بورويس الجنوبية"},{"delegation":{"circonscription":{"circ_id":"240","circ_name":"سليانـــة"},"deleg_id":"56","deleg_name":"بورويس"},"pcenter_id":"010","pcenter_name":"م إبتدائية سيدي بورويس الفلاحي - عين عاشور"},{"delegation":{"circonscription":{"circ_id":"240","circ_name":"سليانـــة"},"deleg_id":"56","deleg_name":"بورويس"},"pcenter_id":"011","pcenter_name":"م إبتدائية محطة الكريب"},{"delegation":{"circonscription":{"circ_id":"240","circ_name":"سليانـــة"},"deleg_id":"56","deleg_name":"بورويس"},"pcenter_id":"091","pcenter_name":"م إعدادية سيدي بورويس(المنطقة البلدية)*"}]